semantif/__init__.py
semantif/config.py
semantif/core.py
semantif/errors.py
semantif/api_clients/__init__.py
semantif/api_clients/openai_client.py
semantif-0.1.1.dist-info/licenses/LICENSE
semantif-0.1.1.dist-info/METADATA
semantif-0.1.1.dist-info/WHEEL
semantif-0.1.1.dist-info/top_level.txt
semantif-0.1.1.dist-info/RECORD
