Metadata-Version: 2.4
Name: semantif
Version: 0.1.1
Summary: Providing a single, intuitive function for semantic judgment.
License: MIT License
Classifier: Programming Language :: Python :: 3
Classifier: Programming Language :: Python :: 3.3
Classifier: Programming Language :: Python :: 3 :: Only
Classifier: Operating System :: OS Independent
Requires-Python: >=3.3
License-File: LICENSE
Dynamic: license-file
